{
  "title": "Empty destructuring patterns should not be used in Vue templates",
  "type": "CODE_SMELL",
  "status": "ready",
  "remediation": {
    "func": "Constant/Issue",
    "constantCost": "2 min"
  },
  "tags": [
    "vue",
    "template",
    "destructuring"
  ],
  "defaultSeverity": "Blocker",
  "ruleSpecification": "RSPEC-7640",
  "sqKey": "S7640",
  "scope": "All",
  "defaultQualityProfiles": [
    "Sonar way"
  ],
  "quickfix": "unknown",
  "code": {
    "impacts": {
      "MAINTAINABILITY": "BLOCKER"
    },
    "attribute": "CLEAR"
  }
}