{
  "title": "Deprecated classes and interfaces should not be extended\/implemented",
  "type": "CODE_SMELL",
  "status": "deprecated",
  "remediation": {
    "func": "Constant\/Issue",
    "constantCost": "30min"
  },
  "tags": [
    
  ],
  "replacementRules": [
    "RSPEC-1874"
  ],
  "coveredLanguages": [
    
  ],
  "defaultSeverity": "Minor",
  "ruleSpecification": "RSPEC-1724",
  "sqKey": "S1724",
  "compatibleLanguages": [
    
  ],
  "scope": "Main",
  "defaultQualityProfiles": [
    
  ]
}
