{"title":"\"ORDER BY\" should be specified for cursors","type":"BUG","status":"ready","remediation":{"func":"Constant/Issue","constantCost":"1h"},"tags":["sql"],"extra":{"replacementRules":[],"legacyKeys":["SQL.CursorDeclaredWithNoOrderByClauseCheck"]},"defaultSeverity":"Major","ruleSpecification":"RSPEC-1592","sqKey":"SQL.CursorDeclaredWithNoOrderByClauseCheck","scope":"Main","defaultQualityProfiles":[],"quickfix":"unknown","allKeys":["SQL.CursorDeclaredWithNoOrderByClauseCheck"],"branch":"master","languagesSupport":[{"name":"cobol","status":"ready"}]}