{
  "title": "Objects or functions with external linkage shall be declared in a header file",
  "type": "CODE_SMELL",
  "status": "closed",
  "remediation": {
    "func": "Constant\/Issue",
    "constantCost": "10mn"
  },
  "tags": [
    "misra"
  ],
  "extra": {
    "coveredLanguages": [

    ],
    "replacementRules": [

    ],
    "legacyKeys": [

    ]
  },
  "defaultSeverity": "Major",
  "ruleSpecification": "RSPEC-827",
  "sqKey": "S827",
  "scope": "Main",
  "defaultQualityProfiles": [

  ]
}
