{
  "title": "Empty throws (\"throw;\") should only be used in the compound statements of catch handlers",
  "type": "BUG",
  "code": {
    "impacts": {
      "RELIABILITY": "HIGH"
    },
    "attribute": "LOGICAL"
  },
  "status": "ready",
  "remediation": {
    "func": "Constant\/Issue",
    "constantCost": "20min"
  },
  "tags": [
    "based-on-misra"
  ],
  "extra": {
    "replacementRules": [

    ],
    "legacyKeys": [
      "EmptyThrowOutsideHandler"
    ]
  },
  "defaultSeverity": "Critical",
  "ruleSpecification": "RSPEC-1039",
  "sqKey": "S1039",
  "scope": "Main",
  "defaultQualityProfiles": [
    "Sonar way",
    "MISRA C++ 2008 recommended"
  ],
  "quickfix": "unknown"
}
