{"title":"Pipeline parameters should not use environment variables in default values","type":"BUG","status":"ready","remediation":{"func":"Constant/Issue","constantCost":"5 min"},"tags":["jenkins","timing"],"defaultSeverity":"Blocker","ruleSpecification":"RSPEC-8353","sqKey":"S8353","scope":"All","defaultQualityProfiles":["Sonar way"],"quickfix":"unknown","code":{"impacts":{"RELIABILITY":"BLOCKER","MAINTAINABILITY":"BLOCKER"},"attribute":"LOGICAL"},"allKeys":["S8353"],"prUrl":"https://github.com/SonarSource/rspec/pull/5988","branch":"rule/add-RSPEC-S8353","languagesSupport":[{"name":"groovy","status":"ready"}]}