{"title":"\"PERFORM PARAGRAPH\" should not be used","type":"CODE_SMELL","status":"ready","remediation":{"func":"Constant/Issue","constantCost":"1h"},"tags":["pitfall"],"extra":{"replacementRules":[],"legacyKeys":["COBOL.PerformThruParagraphMandatoryCheck"]},"defaultSeverity":"Major","ruleSpecification":"RSPEC-1565","sqKey":"COBOL.PerformThruParagraphMandatoryCheck","scope":"Main","defaultQualityProfiles":[],"quickfix":"unknown","allKeys":["COBOL.PerformThruParagraphMandatoryCheck"],"branch":"master","languagesSupport":[{"name":"cobol","status":"ready"}]}