{
  "title": "Number patterns should be regular",
  "type": "CODE_SMELL",
  "status": "ready",
  "remediation": {
    "func": "Constant\/Issue",
    "constantCost": "10min"
  },
  "tags": [
    "suspicious"
  ],
  "replacementRules": [
    
  ],
  "coveredLanguages": [
    "C#",
    "Java"
  ],
  "defaultSeverity": "Critical",
  "ruleSpecification": "RSPEC-3937",
  "sqKey": "S3937",
  "compatibleLanguages": [
    "CSHARPSQUID",
    "JAVA"
  ],
  "scope": "All",
  "defaultQualityProfiles": [
    
  ]
}
