{
  "title": "\"CREATE_TIMER\" should not be used",
  "type": "CODE_SMELL",
  "code": {
    "impacts": {
      "MAINTAINABILITY": "MEDIUM"
    },
    "attribute": "CONVENTIONAL"
  },
  "status": "ready",
  "remediation": {
    "func": "Constant\/Issue",
    "constantCost": "10min"
  },
  "tags": [
    "performance"
  ],
  "extra": {
    "replacementRules": [

    ],
    "legacyKeys": [

    ]
  },
  "defaultSeverity": "Major",
  "ruleSpecification": "RSPEC-4584",
  "sqKey": "S4584",
  "scope": "Main",
  "defaultQualityProfiles": [

  ],
  "quickfix": "unknown"
}
