{"title":"Interface names should comply with a naming convention","type":"CODE_SMELL","code":{"impacts":{"MAINTAINABILITY":"LOW"},"attribute":"IDENTIFIABLE"},"status":"ready","remediation":{"func":"Constant/Issue","constantCost":"10min"},"tags":["convention"],"extra":{"replacementRules":[],"legacyKeys":["InterfaceName"]},"defaultSeverity":"Minor","ruleSpecification":"RSPEC-114","sqKey":"S114","scope":"All","defaultQualityProfiles":["Sonar way"],"quickfix":"unknown","allKeys":["S114","InterfaceName"],"branch":"master","languagesSupport":[{"name":"abap","status":"ready"},{"name":"java","status":"ready"},{"name":"php","status":"ready"},{"name":"swift","status":"ready"},{"name":"vbnet","status":"ready"}]}