{"title":"Deprecated Node.js APIs should not be used","type":"CODE_SMELL","status":"ready","remediation":{"func":"Constant/Issue","constantCost":"5 min"},"tags":["nodejs","deprecated","api"],"defaultSeverity":"Blocker","ruleSpecification":"RSPEC-7658","sqKey":"S7658","scope":"Main","defaultQualityProfiles":["Sonar way"],"quickfix":"unknown","code":{"impacts":{"RELIABILITY":"BLOCKER","MAINTAINABILITY":"BLOCKER"},"attribute":"CONVENTIONAL"},"allKeys":["S7658"],"prUrl":"https://github.com/SonarSource/rspec/pull/5287","branch":"rule/add-RSPEC-S7658","languagesSupport":[{"name":"javascript","status":"ready"}]}