{
  "title": "\"false\" should not be assigned to pointer types",
  "type": "CODE_SMELL",
  "code": {
    "impacts": {
      "MAINTAINABILITY": "HIGH"
    },
    "attribute": "LOGICAL"
  },
  "status": "ready",
  "remediation": {
    "func": "Constant\/Issue",
    "constantCost": "5min"
  },
  "tags": [

  ],
  "extra": {
    "replacementRules": [

    ],
    "legacyKeys": [

    ]
  },
  "defaultSeverity": "Critical",
  "ruleSpecification": "RSPEC-3285",
  "sqKey": "S3285",
  "scope": "Main",
  "defaultQualityProfiles": [
    "Sonar way",
    "MISRA C++ 2008 recommended"
  ],
  "quickfix": "unknown"
}
