{
  "title": "Accessible base classes should not be both \"virtual\" and non-virtual in the same hierarchy",
  "type": "BUG",
  "code": {
    "impacts": {
      "RELIABILITY": "LOW"
    },
    "attribute": "LOGICAL"
  },
  "status": "ready",
  "remediation": {
    "func": "Constant\/Issue",
    "constantCost": "10min"
  },
  "tags": [
    "based-on-misra"
  ],
  "extra": {
    "replacementRules": [

    ],
    "legacyKeys": [

    ]
  },
  "defaultSeverity": "Minor",
  "ruleSpecification": "RSPEC-1013",
  "sqKey": "S1013",
  "scope": "Main",
  "defaultQualityProfiles": [

  ],
  "quickfix": "unknown"
}
