{
  "title": "Blocks containing \"EXECUTE IMMEDIATE\" should trap all exceptions",
  "status": "ready",
  "remediation": {
    "func": "Constant\/Issue",
    "constantCost": "1h"
  },
  "tags": [
    "error-handling"
  ],
  "extra": {
    "coveredLanguages": [
      "PL\/SQL"
    ],
    "replacementRules": [
      
    ]
  },
  "defaultSeverity": "Critical",
  "ruleSpecification": "RSPEC-2461",
  "sqKey": "ExecuteImmediateTrapExceptionsCheck",
  "defaultQualityProfiles": [
    "Sonar way"
  ]
}
