{
  "title": "The address of an automatic variable should not be returned",
  "type": "BUG",
  "status": "ready",
  "remediation": {
    "func": "Constant\/Issue",
    "constantCost": "20min"
  },
  "tags": [
    "based-on-misra",
    "cert"
  ],
  "extra": {
    "replacementRules": [

    ],
    "legacyKeys": [

    ]
  },
  "defaultSeverity": "Major",
  "ruleSpecification": "RSPEC-837",
  "sqKey": "S837",
  "scope": "Main",
  "securityStandards": {
    "CERT": [
      "DCL30-C."
    ]
  },
  "defaultQualityProfiles": [
    "Sonar way"
  ],
  "quickfix": "unknown"
}
