{"title":"Service account permissions should be restricted","type":"VULNERABILITY","status":"ready","remediation":{"func":"Constant/Issue","constantCost":"1h"},"tags":[],"defaultSeverity":"Major","ruleSpecification":"RSPEC-6865","sqKey":"S6865","scope":"All","securityStandards":{"CWE":[306]},"defaultQualityProfiles":["Sonar way"],"quickfix":"unknown","code":{"impacts":{"MAINTAINABILITY":"MEDIUM","SECURITY":"MEDIUM"},"attribute":"COMPLETE"},"allKeys":["S6865"],"branch":"master","languagesSupport":[{"name":"kubernetes","status":"ready"}]}