{
  "title": "Procedures that check parameter count should mark parameters optional",
  "type": "CODE_SMELL",
  "status": "ready",
  "remediation": {
    "func": "Linear",
    "linearDesc": "per parameter",
    "linearFactor": "2min"
  },
  "tags": [
    "api-design"
  ],
  "replacementRules": [
    
  ],
  "coveredLanguages": [
    
  ],
  "defaultSeverity": "Major",
  "ruleSpecification": "RSPEC-3388",
  "sqKey": "S3388",
  "compatibleLanguages": [
    "RPG"
  ],
  "scope": "Main",
  "defaultQualityProfiles": [
    "Sonar way"
  ]
}
