{
  "title": "Constant names should comply with a naming convention",
  "type": "CODE_SMELL",
  "status": "ready",
  "remediation": {
    "func": "Constant\/Issue",
    "constantCost": "2min"
  },
  "tags": [
    "convention"
  ],
  "replacementRules": [
    
  ],
  "coveredLanguages": [
    "Java",
    "PL\/SQL",
    "Flex",
    "PHP",
    "Swift",
    "VB6"
  ],
  "defaultSeverity": "Critical",
  "ruleSpecification": "RSPEC-115",
  "sqKey": "S115",
  "compatibleLanguages": [
    "CPP",
    "PYTHON",
    "CSHARPSQUID",
    "PLSQL",
    "SWIFT",
    "PHP",
    "FLEX",
    "JAVASCRIPT",
    "JAVA",
    "VB"
  ],
  "scope": "All",
  "defaultQualityProfiles": [
    "Sonar way"
  ]
}
