{
  "title": "Allowing requests with excessive content length is security-sensitive",
  "type": "SECURITY_HOTSPOT",
  "status": "ready",
  "remediation": {
    "func": "Constant/Issue",
    "constantCost": "5min"
  },
  "tags": [
    "cwe",
    "cert",
    "owasp-a6"
  ],
  "extra": {
    "coveredLanguages": [
      "C#",
      "Java",
      "VB.Net",
      "JavaScript",
      "PHP"
    ],
    "replacementRules": []
  },
  "defaultSeverity": "Major",
  "ruleSpecification": "RSPEC-5693",
  "sqKey": "S5693",
  "scope": "All",
  "securityStandards": {
    "CWE": [
      400,
      770
    ],
    "OWASP": [
      "A6"
    ]
  },
  "defaultQualityProfiles": [
    "Sonar way"
  ],
  "all_languages": [
    "abap",
    "apex",
    "cfamily",
    "cobol",
    "csharp",
    "css",
    "flex",
    "go",
    "html",
    "java",
    "javascript",
    "kotlin",
    "php",
    "pli",
    "plsql",
    "python",
    "rpg",
    "ruby",
    "rust",
    "scala",
    "solidity",
    "swift",
    "tsql",
    "vb6",
    "vbnet",
    "xml"
  ],
  "allKeys": [
    "S5693"
  ],
  "branch": "master"
}