{
  "title": "Dependencies should not have \"system\" scope",
  "type": "BUG",
  "code": {
    "impacts": {
      "RELIABILITY": "HIGH"
    },
    "attribute": "COMPLETE"
  },
  "status": "ready",
  "remediation": {
    "func": "Constant\/Issue",
    "constantCost": "5min"
  },
  "tags": [
    "maven",
    "lock-in"
  ],
  "extra": {
    "replacementRules": [

    ],
    "legacyKeys": [

    ]
  },
  "defaultSeverity": "Critical",
  "ruleSpecification": "RSPEC-3422",
  "sqKey": "S3422",
  "scope": "All",
  "defaultQualityProfiles": [
    "Sonar way"
  ],
  "quickfix": "unknown"
}
