{
  "title": "Flask forms should validate all user input before processing",
  "type": "VULNERABILITY",
  "status": "ready",
  "remediation": {
    "func": "Constant/Issue",
    "constantCost": "15 min"
  },
  "tags": [
    "flask",
    "input-validation",
    "security"
  ],
  "defaultSeverity": "Blocker",
  "ruleSpecification": "RSPEC-8377",
  "sqKey": "S8377",
  "scope": "Main",
  "defaultQualityProfiles": [
    "Sonar way"
  ],
  "quickfix": "unknown",
  "code": {
    "impacts": {
      "SECURITY": "BLOCKER",
      "RELIABILITY": "HIGH"
    },
    "attribute": "COMPLETE"
  },
  "securityStandards": {
    "OWASP Top 10 2021": [
      "A3"
    ],
    "CWE": [
      20
    ]
  }
}