{
  "title": "Sufficiently restricted arguments should be passed to stream functions",
  "type": "CODE_SMELL",
  "status": "ready",
  "remediation": {
    "func": "Constant\/Issue",
    "constantCost": "10min"
  },
  "tags": [
    "symbolic-execution",
    "suspicious"
  ],
  "extra": {
    "replacementRules": [

    ],
    "legacyKeys": [

    ]
  },
  "defaultSeverity": "Critical",
  "ruleSpecification": "RSPEC-5485",
  "sqKey": "S5485",
  "scope": "All",
  "securityStandards": {
    "CWE": [
      476
    ],
    "CERT": [
      "EXP01-J."
    ]
  },
  "defaultQualityProfiles": [
    "Sonar way",
    "MISRA C++ 2008 recommended"
  ],
  "quickfix": "infeasible"
}
