{"title":"PySpark's \"DataFrame\" column names should be unique","type":"CODE_SMELL","status":"ready","remediation":{"func":"Constant/Issue","constantCost":"5min"},"tags":["data-science","pyspark"],"defaultSeverity":"Major","ruleSpecification":"RSPEC-7469","sqKey":"S7469","scope":"All","defaultQualityProfiles":["Sonar way"],"quickfix":"unknown","code":{"impacts":{"MAINTAINABILITY":"MEDIUM","RELIABILITY":"HIGH"},"attribute":"CONVENTIONAL"},"allKeys":["S7469"],"branch":"master","languagesSupport":[{"name":"python","status":"ready"}]}