{"title":"Boolean expressions should not be gratuitous","type":"CODE_SMELL","code":{"impacts":{"MAINTAINABILITY":"MEDIUM"},"attribute":"LOGICAL"},"status":"ready","remediation":{"func":"Constant/Issue","constantCost":"10min"},"tags":["cwe","suspicious","redundant","symbolic-execution"],"extra":{"replacementRules":[],"legacyKeys":[]},"defaultSeverity":"Major","ruleSpecification":"RSPEC-2589","sqKey":"S2589","scope":"All","securityStandards":{"CWE":[489,571,570]},"defaultQualityProfiles":["Sonar way"],"quickfix":"unknown","allKeys":["S2589"],"branch":"master","languagesSupport":[{"name":"cfamily","status":"closed"},{"name":"cobol","status":"ready"},{"name":"csharp","status":"ready"},{"name":"java","status":"ready"},{"name":"javascript","status":"ready"},{"name":"python","status":"ready"},{"name":"rust","status":"ready"},{"name":"vbnet","status":"ready"}]}