{
  "title": "\"STOP RUN\" or \"GOBACK\" should be the last statement of a sequence",
  "type": "BUG",
  "code": {
    "impacts": {
      "RELIABILITY": "MEDIUM"
    },
    "attribute": "CLEAR"
  },
  "status": "ready",
  "remediation": {
    "func": "Constant\/Issue",
    "constantCost": "1h"
  },
  "tags": [
    "unused"
  ],
  "extra": {
    "replacementRules": [

    ],
    "legacyKeys": [
      "StopRunUsageCheck",
      "COBOL.StopRunUsageCheck"
    ]
  },
  "defaultSeverity": "Major",
  "ruleSpecification": "RSPEC-1475",
  "sqKey": "COBOL.StopRunUsageCheck",
  "scope": "Main",
  "defaultQualityProfiles": [
    "Sonar way"
  ],
  "quickfix": "unknown"
}
