{
  "title": "Use \"[[\" instead of \"[\" for conditional tests",
  "type": "CODE_SMELL",
  "status": "ready",
  "remediation": {
    "func": "Constant/Issue",
    "constantCost": "2 min"
  },
  "tags": [
    "bash",
    "shell",
    "scripting",
    "best-practices"
  ],
  "defaultSeverity": "Major",
  "ruleSpecification": "RSPEC-7688",
  "sqKey": "S7688",
  "scope": "All",
  "defaultQualityProfiles": [
    "Sonar way"
  ],
  "quickfix": "unknown",
  "code": {
    "impacts": {
      "RELIABILITY": "HIGH"
    },
    "attribute": "CONVENTIONAL"
  }
}
