{
  "title": "\"LOOP ... END LOOP;\" constructs should be avoided",
  "type": "CODE_SMELL",
  "status": "ready",
  "remediation": {
    "func": "Constant/Issue",
    "constantCost": "1h"
  },
  "tags": [
    "pitfall"
  ],
  "extra": {
    "coveredLanguages": [
      "PL/SQL",
      "VB.Net"
    ],
    "replacementRules": []
  },
  "defaultSeverity": "Critical",
  "ruleSpecification": "RSPEC-2340",
  "sqKey": "LoopAvoidSimpleLoopCheck",
  "scope": "Main",
  "defaultQualityProfiles": [
    "Sonar way"
  ],
  "all_languages": [
    "plsql",
    "vbnet"
  ],
  "allKeys": [
    "LoopAvoidSimpleLoopCheck",
    "S2340"
  ],
  "branch": "master"
}