{
  "title": "Same buffer should not be used both for the output and input of \"s[n]printf(...)\"",
  "type": "BUG",
  "code": {
    "impacts": {
      "RELIABILITY": "HIGH"
    },
    "attribute": "LOGICAL"
  },
  "status": "ready",
  "remediation": {
    "func": "Constant\/Issue",
    "constantCost": "10min"
  },
  "tags": [

  ],
  "extra": {
    "replacementRules": [

    ],
    "legacyKeys": [

    ]
  },
  "defaultSeverity": "Critical",
  "ruleSpecification": "RSPEC-1180",
  "sqKey": "S1180",
  "scope": "Main",
  "defaultQualityProfiles": [
    "Sonar way",
    "MISRA C++ 2008 recommended"
  ],
  "quickfix": "unknown"
}
