{
  "title": "Values passed to XQuery commands should be sanitized",
  "type": "VULNERABILITY",
  "status": "ready",
  "remediation": {
    "func": "Constant\/Issue",
    "constantCost": "20min"
  },
  "tags": [
    "cwe",
    "owasp-a1"
  ],
  "extra": {
    "coveredLanguages": [
      
    ],
    "replacementRules": [
      
    ]
  },
  "defaultSeverity": "Blocker",
  "ruleSpecification": "RSPEC-2086",
  "sqKey": "S2086",
  "scope": "Main",
  "securityStandards": {
    "CWE": [
      652
    ],
    "OWASP": [
      "A1"
    ]
  },
  "defaultQualityProfiles": [
    "Sonar way",
    "MISRA C++ 2008 recommended"
  ]
}
