{
  "title": "Email messages should be sent in batches",
  "type": "BUG",
  "status": "ready",
  "remediation": {
    "func": "Constant\/Issue",
    "constantCost": "10min"
  },
  "tags": [
    "unpredictable",
    "governor-limits"
  ],
  "extra": {
    "coveredLanguages": [

    ],
    "replacementRules": [

    ]
  },
  "defaultSeverity": "Critical",
  "ruleSpecification": "RSPEC-5498",
  "sqKey": "S5498",
  "scope": "Main",
  "defaultQualityProfiles": [
    "Sonar way"
  ],
  "legacyKeys": [

  ]
}
