{
  "title": "Disabling strict HTTP no-referrer policy is security-sensitive",
  "type": "SECURITY_HOTSPOT",
  "status": "ready",
  "remediation": {
    "func": "Constant\/Issue",
    "constantCost": "5min"
  },
  "tags": [
    "cwe",
    "owasp-a3"
  ],
  "replacementRules": [
    
  ],
  "coveredLanguages": [
    
  ],
  "defaultSeverity": "Minor",
  "ruleSpecification": "RSPEC-5736",
  "sqKey": "S5736",
  "compatibleLanguages": [
    "RUBY",
    "JAVA",
    "WEB",
    "PHP",
    "PYTHON",
    "SCALA",
    "JAVASCRIPT",
    "TYPESCRIPT",
    "PLI",
    "KOTLIN",
    "FLEX",
    "APEX",
    "XML",
    "COBOL",
    "GO",
    "VBNET",
    "TSQL",
    "CSHARPSQUID",
    "ABAP",
    "RUST",
    "CSS",
    "SOLIDITY",
    "CPP",
    "PLSQL",
    "C",
    "SWIFT",
    "OBJC",
    "RPG",
    "VB"
  ],
  "scope": "Main",
  "securityStandards": {
    "CWE": [
      200
    ],
    "OWASP": [
      "A3"
    ]
  },
  "defaultQualityProfiles": [
    "Sonar way"
  ]
}
