{
  "title": "The sign of an unsigned variable should not be tested",
  "type": "CODE_SMELL",
  "status": "superseded",
  "remediation": {
    "func": "Constant\/Issue",
    "constantCost": "5min"
  },
  "tags": [
    "pitfall"
  ],
  "extra": {
    "coveredLanguages": [
      "C++",
      "C",
      "Objective-C"
    ],
    "replacementRules": [
      "RSPEC-2583"
    ]
  },
  "defaultSeverity": "Critical",
  "ruleSpecification": "RSPEC-1768",
  "sqKey": "S1768",
  "scope": "Main",
  "defaultQualityProfiles": [
    "Sonar way"
  ]
}
