{
  "title": "Digraphs should not be used",
  "type": "CODE_SMELL",
  "status": "ready",
  "remediation": {
    "func": "Constant\/Issue",
    "constantCost": "5min"
  },
  "tags": [
    "based-on-misra",
    "obsolete"
  ],
  "extra": {
    "coveredLanguages": [
      "C++",
      "C",
      "Objective-C"
    ],
    "replacementRules": [

    ],
    "legacyKeys": [
      "DigraphUsage"
    ]
  },
  "defaultSeverity": "Blocker",
  "ruleSpecification": "RSPEC-798",
  "sqKey": "DigraphUsage",
  "scope": "Main",
  "defaultQualityProfiles": [
    "Sonar way",
    "MISRA C++ 2008 recommended"
  ]
}
