{
  "title": "Special identifiers should not be bound or assigned",
  "type": "BUG",
  "status": "ready",
  "remediation": {
    "func": "Constant\/Issue",
    "constantCost": "10min"
  },
  "tags": [
    "pitfall"
  ],
  "replacementRules": [
    
  ],
  "coveredLanguages": [
    "JavaScript"
  ],
  "defaultSeverity": "Major",
  "ruleSpecification": "RSPEC-2137",
  "sqKey": "S2137",
  "compatibleLanguages": [
    "JAVASCRIPT"
  ],
  "scope": "Main",
  "defaultQualityProfiles": [
    "Sonar way recommended",
    "Sonar way"
  ]
}
