{
  "title": "ScopedValue instances should be declared as static final fields",
  "type": "CODE_SMELL",
  "status": "ready",
  "remediation": {
    "func": "Constant/Issue",
    "constantCost": "5 min"
  },
  "tags": [
    "java21",
    "convention"
  ],
  "defaultSeverity": "Blocker",
  "ruleSpecification": "RSPEC-8144",
  "sqKey": "S8144",
  "scope": "Main",
  "defaultQualityProfiles": [
    "Sonar way"
  ],
  "quickfix": "unknown",
  "code": {
    "impacts": {
      "RELIABILITY": "BLOCKER",
      "MAINTAINABILITY": "BLOCKER"
    },
    "attribute": "CONVENTIONAL"
  }
}