{"title":"Dataset \"__getitem__\" methods should return only serializable types","type":"BUG","status":"ready","remediation":{"func":"Constant/Issue","constantCost":"15 min"},"tags":["pytorch","serialization","runtime-error"],"defaultSeverity":"Blocker","ruleSpecification":"RSPEC-7712","sqKey":"S7712","scope":"Main","defaultQualityProfiles":["Sonar way"],"quickfix":"unknown","code":{"impacts":{"RELIABILITY":"BLOCKER","MAINTAINABILITY":"BLOCKER"},"attribute":"LOGICAL"},"allKeys":["S7712"],"prUrl":"https://github.com/SonarSource/rspec/pull/5367","branch":"rule/add-RSPEC-S7712","languagesSupport":[{"name":"python","status":"ready"}]}