{
  "title": "New types should be defined in copybooks",
  "type": "CODE_SMELL",
  "status": "ready",
  "remediation": {
    "func": "Constant\/Issue",
    "constantCost": "1h"
  },
  "tags": [
    "bad-practice"
  ],
  "replacementRules": [
    
  ],
  "coveredLanguages": [
    "Cobol"
  ],
  "defaultSeverity": "Major",
  "ruleSpecification": "RSPEC-1584",
  "sqKey": "COBOL.TypedefUsageCheck",
  "compatibleLanguages": [
    "COBOL"
  ],
  "scope": "Main",
  "defaultQualityProfiles": [
    
  ]
}
