{
  "title": "First level data items should follow a naming convention",
  "type": "CODE_SMELL",
  "status": "ready",
  "remediation": {
    "func": "Constant\/Issue",
    "constantCost": "30min"
  },
  "tags": [
    "convention"
  ],
  "replacementRules": [
    
  ],
  "coveredLanguages": [
    "Cobol"
  ],
  "defaultSeverity": "Minor",
  "ruleSpecification": "RSPEC-1580",
  "sqKey": "COBOL.FirstLevelDataItemNamingCheck",
  "compatibleLanguages": [
    "COBOL"
  ],
  "scope": "Main",
  "defaultQualityProfiles": [
    
  ]
}
