{
  "title": "\"Asc[W]\" should not be called on string constants",
  "type": "CODE_SMELL",
  "code": {
    "impacts": {
      "MAINTAINABILITY": "MEDIUM"
    },
    "attribute": "EFFICIENT"
  },
  "status": "ready",
  "remediation": {
    "func": "Constant\/Issue",
    "constantCost": "3min"
  },
  "tags": [
    "performance"
  ],
  "extra": {
    "replacementRules": [

    ],
    "legacyKeys": [

    ]
  },
  "defaultSeverity": "Major",
  "ruleSpecification": "RSPEC-1652",
  "sqKey": "S1652",
  "scope": "Main",
  "defaultQualityProfiles": [
    "Sonar way"
  ],
  "quickfix": "unknown"
}
