{
  "title": "Column references should not have more than two-parts",
  "type": "CODE_SMELL",
  "code": {
    "impacts": {
      "MAINTAINABILITY": "LOW"
    },
    "attribute": "CONVENTIONAL"
  },
  "status": "ready",
  "remediation": {
    "func": "Constant\/Issue",
    "constantCost": "1min"
  },
  "tags": [
    "obsolete"
  ],
  "extra": {
    "replacementRules": [

    ],
    "legacyKeys": [

    ]
  },
  "defaultSeverity": "Minor",
  "ruleSpecification": "RSPEC-4149",
  "sqKey": "S4149",
  "scope": "All",
  "defaultQualityProfiles": [
    "Sonar way"
  ],
  "quickfix": "unknown"
}
