{
  "title": "Controller actions should not call render or redirect multiple times",
  "type": "BUG",
  "status": "ready",
  "remediation": {
    "func": "Constant/Issue",
    "constantCost": "5 min"
  },
  "tags": [
    "rails",
    "controller"
  ],
  "defaultSeverity": "Blocker",
  "ruleSpecification": "RSPEC-7851",
  "sqKey": "S7851",
  "scope": "Main",
  "defaultQualityProfiles": [
    "Sonar way"
  ],
  "quickfix": "unknown",
  "code": {
    "impacts": {
      "RELIABILITY": "BLOCKER",
      "MAINTAINABILITY": "BLOCKER"
    },
    "attribute": "LOGICAL"
  }
}