{
  "title": "Forwarding client IP address is security-sensitive",
  "type": "SECURITY_HOTSPOT",
  "status": "ready",
  "remediation": {
    "func": "Constant\/Issue",
    "constantCost": "5min"
  },
  "tags": [
    "privacy",
    "owasp-a3"
  ],
  "replacementRules": [
    
  ],
  "coveredLanguages": [
    
  ],
  "defaultSeverity": "Minor",
  "ruleSpecification": "RSPEC-5759",
  "sqKey": "S5759",
  "compatibleLanguages": [
    "JAVA",
    "CPP",
    "C",
    "PHP",
    "PYTHON",
    "JAVASCRIPT",
    "TYPESCRIPT",
    "CSHARPSQUID"
  ],
  "scope": "Main",
  "securityStandards": {
    "OWASP": [
      "A3"
    ]
  },
  "defaultQualityProfiles": [
    "Sonar way recommended",
    "Sonar way"
  ]
}
