{
  "title": "\"NULL\" should not be compared directly",
  "type": "BUG",
  "status": "ready",
  "remediation": {
    "func": "Constant\/Issue",
    "constantCost": "10min"
  },
  "tags": [
    "sql"
  ],
  "extra": {
    "coveredLanguages": [
      "T-SQL",
      "PL\/SQL",
      "Cobol"
    ],
    "replacementRules": [

    ]
  },
  "defaultSeverity": "Major",
  "ruleSpecification": "RSPEC-2527",
  "sqKey": "S2527",
  "scope": "Main",
  "defaultQualityProfiles": [
    "Sonar way"
  ],
  "legacyKeys": [
    "NullComparison"
  ]
}
