{
  "title": "Appropriate size arguments should be passed to \"strncat\" and \"strlcpy\"",
  "type": "CODE_SMELL",
  "status": "ready",
  "remediation": {
    "func": "Constant\/Issue",
    "constantCost": "5min"
  },
  "tags": [
    "symbolic-execution",
    "suspicious"
  ],
  "replacementRules": [
    
  ],
  "coveredLanguages": [
    "C++",
    "C",
    "Objective-C"
  ],
  "defaultSeverity": "Major",
  "ruleSpecification": "RSPEC-5273",
  "sqKey": "S5273",
  "compatibleLanguages": [
    "CPP",
    "C",
    "OBJC"
  ],
  "scope": "Main",
  "defaultQualityProfiles": [
    "Sonar way",
    "MISRA C++ 2008 recommended"
  ]
}
