{"title":"Scale should not be specified for float types","type":"BUG","status":"ready","remediation":{"func":"Constant/Issue","constantCost":"5min"},"tags":[],"extra":{"replacementRules":[],"legacyKeys":["FloatWithScaleUsageCheck"]},"defaultSeverity":"Blocker","ruleSpecification":"RSPEC-2463","sqKey":"FloatWithScaleUsageCheck","scope":"Main","defaultQualityProfiles":["Sonar way"],"quickfix":"unknown","allKeys":["FloatWithScaleUsageCheck"],"branch":"master","languagesSupport":[{"name":"plsql","status":"ready"}]}