{
  "title": "\"GOTO\" should not be used within loops",
  "type": "CODE_SMELL",
  "status": "ready",
  "remediation": {
    "func": "Constant\/Issue",
    "constantCost": "1h"
  },
  "tags": [
    "pitfall"
  ],
  "replacementRules": [
    
  ],
  "coveredLanguages": [
    "PL\/SQL"
  ],
  "defaultSeverity": "Major",
  "ruleSpecification": "RSPEC-2469",
  "sqKey": "GotoInLoopCheck",
  "compatibleLanguages": [
    "PLSQL"
  ],
  "scope": "Main",
  "defaultQualityProfiles": [
    "Sonar way"
  ]
}
