{"title":"A single L in a literal suffix should only be used for long values","type":"CODE_SMELL","status":"ready","remediation":{"func":"Constant/Issue","constantCost":"5min"},"tags":["since-c++11"],"defaultSeverity":"Minor","ruleSpecification":"RSPEC-6996","sqKey":"S6996","scope":"All","defaultQualityProfiles":["Sonar way"],"quickfix":"covered","code":{"impacts":{"MAINTAINABILITY":"LOW"},"attribute":"CLEAR"},"allKeys":["S6996"],"branch":"master","languagesSupport":[{"name":"cfamily","status":"ready"}]}